ravanan/__init__.py
ravanan/__main__.py
ravanan/main.py
ravanan/browser/__init__.py
ravanan/browser/fetcher.py
ravanan/browser/navigator.py
ravanan/browser/parser.py
ravanan/browser/renderer.py
ravanan/utils/__init__.py
ravanan/utils/banner.py
ravanan/utils/history.py
ravanan-1.0.5.dist-info/licenses/LICENSE
ravanan-1.0.5.dist-info/METADATA
ravanan-1.0.5.dist-info/WHEEL
ravanan-1.0.5.dist-info/entry_points.txt
ravanan-1.0.5.dist-info/top_level.txt
ravanan-1.0.5.dist-info/RECORD
