Metadata-Version: 2.4
Name: ravanan
Version: 1.0.5
Summary: The 10-Headed Web Browser - A powerful text-based browser for the terminal
Home-page: https://github.com/krishna182005/ravanan
Author: Krishna D
Project-URL: Bug Reports, https://github.com/krishna182005/ravanan/issues
Project-URL: Source, https://github.com/krishna182005/ravanan
Project-URL: Documentation, https://github.com/krishna182005/ravanan#readme
Project-URL: Changelog, https://github.com/krishna182005/ravanan/blob/main/CHANGELOG.md
Keywords: browser,terminal,cli,text-based,lynx,web,http,https,ravanan,ravana,10-headed,tui,console,accessibility
Classifier: Development Status :: 5 - Production/Stable
Classifier: Intended Audience :: Developers
Classifier: Intended Audience :: End Users/Desktop
Classifier: Intended Audience :: System Administrators
Classifier: Topic :: Internet :: WWW/HTTP :: Browsers
Classifier: Topic :: Terminals
Classifier: Topic :: Text Processing :: Markup :: HTML
Classifier: License :: OSI Approved :: MIT License
Classifier: Programming Language :: Python :: 3
Classifier: Programming Language :: Python :: 3.8
Classifier: Programming Language :: Python :: 3.9
Classifier: Programming Language :: Python :: 3.10
Classifier: Programming Language :: Python :: 3.11
Classifier: Programming Language :: Python :: 3.12
Classifier: Programming Language :: Python :: 3 :: Only
Classifier: Operating System :: OS Independent
Classifier: Operating System :: Microsoft :: Windows
Classifier: Operating System :: POSIX :: Linux
Classifier: Operating System :: MacOS
Classifier: Environment :: Console
Classifier: Natural Language :: English
Requires-Python: >=3.8
License-File: LICENSE
Requires-Dist: requests>=2.31.0
Requires-Dist: beautifulsoup4>=4.12.0
Requires-Dist: rich>=13.0.0
Requires-Dist: lxml>=4.9.0
Requires-Dist: PySocks>=1.7.1
Dynamic: author
Dynamic: classifier
Dynamic: description
Dynamic: description-content-type
Dynamic: home-page
Dynamic: keywords
Dynamic: license-file
Dynamic: project-url
Dynamic: requires-dist
Dynamic: requires-python
Dynamic: summary
